qudb/__init__.py
qudb/commands.py
qudb/models.py
qudb/qm.py
qudb-0.6.dist-info/DESCRIPTION.rst
qudb-0.6.dist-info/METADATA
qudb-0.6.dist-info/RECORD
qudb-0.6.dist-info/WHEEL
qudb-0.6.dist-info/entry_points.txt
qudb-0.6.dist-info/metadata.json
qudb-0.6.dist-info/top_level.txt
