Metadata-Version: 2.0
Name: qudb
Version: 0.6
Summary: qudb: Question Database
Home-page: https://bitbucket.org/akhayyat/qudb
Author: Ahmad Khayyat
Author-email: akhayyat@gmail.com
License: BSD
Platform: UNKNOWN
Classifier: Development Status :: 4 - Beta
Classifier: Environment :: Console
Classifier: Intended Audience :: Education
Classifier: License :: OSI Approved :: BSD License
Classifier: Programming Language :: Python :: 3
Classifier: Programming Language :: Python :: 3 :: Only
Classifier: Topic :: Education
Classifier: Topic :: Education :: Computer Aided Instruction (CAI)
Classifier: Topic :: Software Development :: Libraries
Classifier: Topic :: Utilities
Requires-Dist: jinja2
Requires-Dist: sqlalchemy
Provides-Extra: import_export
Requires-Dist: pyyaml (>=3.11); extra == 'import_export'
